g3_metaconfig/__init__.py
g3_metaconfig/configs.py
g3_metaconfig/metaclass.py
g3_metaconfig/param.py
g3_metaconfig/tests/__init__.py
g3_metaconfig/tests/test_all.py
g3_metaconfig-1.1.1.dist-info/LICENSE.txt
g3_metaconfig-1.1.1.dist-info/METADATA
g3_metaconfig-1.1.1.dist-info/WHEEL
g3_metaconfig-1.1.1.dist-info/top_level.txt
g3_metaconfig-1.1.1.dist-info/RECORD
